yt_xarray/__init__.py
yt_xarray/sample_data.py
yt_xarray/transformations.py
yt_xarray/yt_xarray.py
yt_xarray/accessor/__init__.py
yt_xarray/accessor/_readers.py
yt_xarray/accessor/_xr_to_yt.py
yt_xarray/accessor/accessor.py
yt_xarray/tests/__init__.py
yt_xarray/tests/test_accesor.py
yt_xarray/tests/test_chunking.py
yt_xarray/tests/test_grid_decomposition.py
yt_xarray/tests/test_optional_imports.py
yt_xarray/tests/test_sample_data.py
yt_xarray/tests/test_transformations.py
yt_xarray/tests/test_utilities.py
yt_xarray/tests/test_xr_to_yt.py
yt_xarray/tests/test_yt_wrappers.py
yt_xarray/utilities/__init__.py
yt_xarray/utilities/_grid_decomposition.py
yt_xarray/utilities/_utilities.py
yt_xarray/utilities/logging.py
yt_xarray-0.4.1.dist-info/licenses/AUTHORS.md
yt_xarray-0.4.1.dist-info/licenses/LICENSE
yt_xarray-0.4.1.dist-info/METADATA
yt_xarray-0.4.1.dist-info/WHEEL
yt_xarray-0.4.1.dist-info/top_level.txt
yt_xarray-0.4.1.dist-info/RECORD
