Metadata-Version: 2.4
Name: yt_xarray
Version: 0.4.1
Summary: interface between yt and xarray
Author-email: Chris Havlin <chris.havlin@gmail.com>
Project-URL: Homepage, https://github.com/data-exp-lab/yt_xarray
Project-URL: Bug Tracker, https://github.com/data-exp-lab/yt_xarray/issues
Classifier: Development Status :: 4 - Beta
Classifier: Intended Audience :: Developers
Classifier: License :: OSI Approved :: MIT License
Classifier: Natural Language :: English
Classifier: Programming Language :: Python :: 3
Classifier: Programming Language :: Python :: 3.10
Classifier: Programming Language :: Python :: 3.11
Classifier: Programming Language :: Python :: 3.12
Requires-Python: >=3.10
License-File: LICENSE
License-File: AUTHORS.md
Requires-Dist: yt>=4.2.0
Requires-Dist: h5py>=3.4.0
Requires-Dist: pooch>=1.5.1
Requires-Dist: xarray!=v2025.06.0
Provides-Extra: full
Requires-Dist: netCDF4; extra == "full"
Requires-Dist: scipy; extra == "full"
Requires-Dist: dask[complete]; extra == "full"
Requires-Dist: cf_xarray; extra == "full"
Provides-Extra: test
Requires-Dist: pytest; extra == "test"
Requires-Dist: pytest-cov; extra == "test"
Requires-Dist: cartopy; extra == "test"
Provides-Extra: docs
Requires-Dist: Sphinx==7.2.6; extra == "docs"
Requires-Dist: jinja2==3.1.2; extra == "docs"
Requires-Dist: nbsphinx==0.9.3; extra == "docs"
Dynamic: license-file
